tests/__init__.py
tests/test_export.py
tests/test_train.py
tests/contrib/__init__.py
tests/contrib/test_pretrained.py
tests/data/__init__.py
tests/data/test_classes.py
tests/data/test_containers.py
tests/data/io/__init__.py
tests/data/io/test_download.py
tests/data/io/test_io.py
tests/modules/__init__.py
tests/modules/test_loss.py
tests/modules/conv/__init__.py
tests/modules/conv/test_mixconv.py
tests/modules/conv/test_utils.py
tests/utils/__init__.py
tests/utils/test_registry.py
yann/__init__.py
yann/cli.py
yann/cuda.py
yann/exceptions.py
yann/export.py
yann/hooks.py
yann/init.py
yann/log.py
yann/lr.py
yann/metrics.py
yann/params.py
yann/perf.py
yann/schedule.py
yann/spec.py
yann/testing.py
yann/typedefs.py
yann/blueprints/__init__.py
yann/blueprints/multiclass.py
yann/blueprints/multilabel.py
yann/blueprints/vision/__init__.py
yann/blueprints/vision/recognition.py
yann/callbacks/__init__.py
yann/callbacks/base.py
yann/callbacks/checkpoint.py
yann/callbacks/eval.py
yann/callbacks/history.py
yann/callbacks/logging.py
yann/callbacks/lr.py
yann/callbacks/outputs.py
yann/callbacks/progbar.py
yann/callbacks/stop.py
yann/callbacks/swa.py
yann/callbacks/tensorboard.py
yann/callbacks/timing.py
yann/config/__init__.py
yann/config/registry.py
yann/config/setup.py
yann/contrib/__init__.py
yann/contrib/gcp.py
yann/contrib/pretrained.py
yann/contrib/slack.py
yann/data/__init__.py
yann/data/batch.py
yann/data/classes.py
yann/data/collate.py
yann/data/containers.py
yann/data/images.py
yann/data/loaders.py
yann/data/metrics.py
yann/data/sampler.py
yann/data/serialize.py
yann/data/transform.py
yann/data/utils.py
yann/data/io/__init__.py
yann/data/io/download.py
yann/data/search/__init__.py
yann/data/search/annoy.py
yann/data/search/base.py
yann/data/search/inverted_index.py
yann/data/storage/__init__.py
yann/data/storage/lmdb.py
yann/data/storage/parquet.py
yann/datasets/__init__.py
yann-0.0.40.dist-info/DESCRIPTION.rst
yann-0.0.40.dist-info/METADATA
yann-0.0.40.dist-info/RECORD
yann-0.0.40.dist-info/WHEEL
yann-0.0.40.dist-info/entry_points.txt
yann-0.0.40.dist-info/metadata.json
yann-0.0.40.dist-info/top_level.txt
