Metadata-Version: 2.0
Name: yann
Version: 0.0.40
Summary: yet another neural network library
Home-page: https://github.com/michalwols/yann
Author: Michal Wolski
Author-email: michal@bite.ai
License: MIT
Platform: UNKNOWN
Requires-Python: >=3.6
Provides-Extra: cli
Provides-Extra: pretrainedmodels
Requires-Dist: numpy
Requires-Dist: scipy
Requires-Dist: scikit-learn
Requires-Dist: torch (>=1.0.0)
Requires-Dist: matplotlib
Requires-Dist: torchvision
Requires-Dist: tqdm
Provides-Extra: cli
Requires-Dist: click (>=6.7); extra == 'cli'
Provides-Extra: pretrainedmodels
Requires-Dist: pretrainedmodels; extra == 'pretrainedmodels'
